[
  {
    "id": "4abfd2d2-2d2d-4a47-8a8e-9a9d2d61cf64",
    "user_id": "6262311d-4b09-425f-bc6a-b4fb83fa253c",
    "name": "Genel Satış",
    "type": "income",
    "color": "#16a34a",
    "icon": "ShoppingCart",
    "is_default": true,
    "is_active": true,
    "created_at": "2026-01-23T22:13:59.967Z",
    "updated_at": "2026-01-23T22:13:59.967Z",
    "deleted_at": null,
    "expense_type": null,
    "default_channel_id": null,
    "service_commission_rate": "0.00",
    "courier_service_rate": "0.00"
  },
  {
    "id": "091c3ff2-bf95-4175-a411-629644b3f46e",
    "user_id": "6262311d-4b09-425f-bc6a-b4fb83fa253c",
    "name": "Hizmet Geliri",
    "type": "income",
    "color": "#16a34a",
    "icon": "Briefcase",
    "is_default": true,
    "is_active": true,
    "created_at": "2026-01-23T22:13:59.969Z",
    "updated_at": "2026-01-23T22:13:59.969Z",
    "deleted_at": null,
    "expense_type": null,
    "default_channel_id": null,
    "service_commission_rate": "0.00",
    "courier_service_rate": "0.00"
  },
  {
    "id": "e31d73d5-b86a-402d-91a5-1a515d811916",
    "user_id": "6262311d-4b09-425f-bc6a-b4fb83fa253c",
    "name": "Kira",
    "type": "expense",
    "color": "#dc2626",
    "icon": "Home",
    "is_default": true,
    "is_active": true,
    "created_at": "2026-01-23T22:13:59.970Z",
    "updated_at": "2026-01-23T22:13:59.970Z",
    "deleted_at": null,
    "expense_type": null,
    "default_channel_id": null,
    "service_commission_rate": "0.00",
    "courier_service_rate": "0.00"
  },
  {
    "id": "0ad52b19-afbb-4c34-b8c9-2f4d3383232d",
    "user_id": "6262311d-4b09-425f-bc6a-b4fb83fa253c",
    "name": "Fatura (Elektrik/Su)",
    "type": "expense",
    "color": "#dc2626",
    "icon": "Zap",
    "is_default": true,
    "is_active": true,
    "created_at": "2026-01-23T22:13:59.971Z",
    "updated_at": "2026-01-23T22:13:59.971Z",
    "deleted_at": null,
    "expense_type": null,
    "default_channel_id": null,
    "service_commission_rate": "0.00",
    "courier_service_rate": "0.00"
  },
  {
    "id": "4d9d8887-43d0-4f3d-859e-f379fe87a58a",
    "user_id": "6262311d-4b09-425f-bc6a-b4fb83fa253c",
    "name": "Personel Maaşı",
    "type": "expense",
    "color": "#dc2626",
    "icon": "Users",
    "is_default": true,
    "is_active": true,
    "created_at": "2026-01-23T22:13:59.972Z",
    "updated_at": "2026-01-23T22:13:59.972Z",
    "deleted_at": null,
    "expense_type": null,
    "default_channel_id": null,
    "service_commission_rate": "0.00",
    "courier_service_rate": "0.00"
  },
  {
    "id": "b6cf98bc-1c13-4a20-8839-7aa0d56a90a4",
    "user_id": "6262311d-4b09-425f-bc6a-b4fb83fa253c",
    "name": "Malzeme Alımı",
    "type": "expense",
    "color": "#dc2626",
    "icon": "Package",
    "is_default": true,
    "is_active": true,
    "created_at": "2026-01-23T22:13:59.973Z",
    "updated_at": "2026-01-23T22:13:59.973Z",
    "deleted_at": null,
    "expense_type": null,
    "default_channel_id": null,
    "service_commission_rate": "0.00",
    "courier_service_rate": "0.00"
  },
  {
    "id": "162e2555-b4df-4009-8dc1-756615e339be",
    "user_id": "6262311d-4b09-425f-bc6a-b4fb83fa253c",
    "name": "Diğer Giderler",
    "type": "expense",
    "color": "#dc2626",
    "icon": "MoreHorizontal",
    "is_default": true,
    "is_active": true,
    "created_at": "2026-01-23T22:13:59.973Z",
    "updated_at": "2026-01-23T22:13:59.973Z",
    "deleted_at": null,
    "expense_type": null,
    "default_channel_id": null,
    "service_commission_rate": "0.00",
    "courier_service_rate": "0.00"
  },
  {
    "id": "caffca01-efb4-47b3-bc2c-fd1a2422a23a",
    "user_id": "6001e1b4-662c-4ea7-ac74-c4ad74aeb52f",
    "name": "Genel Satış",
    "type": "income",
    "color": "#16a34a",
    "icon": "ShoppingCart",
    "is_default": true,
    "is_active": true,
    "created_at": "2026-01-23T22:16:16.210Z",
    "updated_at": "2026-01-23T22:16:16.210Z",
    "deleted_at": null,
    "expense_type": null,
    "default_channel_id": null,
    "service_commission_rate": "0.00",
    "courier_service_rate": "0.00"
  },
  {
    "id": "80f02c9f-f657-4551-96c5-d66cc8441619",
    "user_id": "6001e1b4-662c-4ea7-ac74-c4ad74aeb52f",
    "name": "Hizmet Geliri",
    "type": "income",
    "color": "#16a34a",
    "icon": "Briefcase",
    "is_default": true,
    "is_active": true,
    "created_at": "2026-01-23T22:16:16.212Z",
    "updated_at": "2026-01-23T22:16:16.212Z",
    "deleted_at": null,
    "expense_type": null,
    "default_channel_id": null,
    "service_commission_rate": "0.00",
    "courier_service_rate": "0.00"
  },
  {
    "id": "1291fa22-e714-40bc-8f08-f539a963e0c3",
    "user_id": "6001e1b4-662c-4ea7-ac74-c4ad74aeb52f",
    "name": "Kira",
    "type": "expense",
    "color": "#dc2626",
    "icon": "Home",
    "is_default": true,
    "is_active": true,
    "created_at": "2026-01-23T22:16:16.212Z",
    "updated_at": "2026-01-23T22:16:16.212Z",
    "deleted_at": null,
    "expense_type": null,
    "default_channel_id": null,
    "service_commission_rate": "0.00",
    "courier_service_rate": "0.00"
  },
  {
    "id": "a654ed25-09de-4d9b-a5ed-eeac5ac208b7",
    "user_id": "6001e1b4-662c-4ea7-ac74-c4ad74aeb52f",
    "name": "Fatura (Elektrik/Su)",
    "type": "expense",
    "color": "#dc2626",
    "icon": "Zap",
    "is_default": true,
    "is_active": true,
    "created_at": "2026-01-23T22:16:16.213Z",
    "updated_at": "2026-01-23T22:16:16.213Z",
    "deleted_at": null,
    "expense_type": null,
    "default_channel_id": null,
    "service_commission_rate": "0.00",
    "courier_service_rate": "0.00"
  },
  {
    "id": "1ef0cde9-1bab-44b7-9176-42cd786bf1a2",
    "user_id": "6001e1b4-662c-4ea7-ac74-c4ad74aeb52f",
    "name": "Personel Maaşı",
    "type": "expense",
    "color": "#dc2626",
    "icon": "Users",
    "is_default": true,
    "is_active": true,
    "created_at": "2026-01-23T22:16:16.214Z",
    "updated_at": "2026-01-23T22:16:16.214Z",
    "deleted_at": null,
    "expense_type": null,
    "default_channel_id": null,
    "service_commission_rate": "0.00",
    "courier_service_rate": "0.00"
  },
  {
    "id": "778e0e6f-a8f5-410c-b3cd-b9f298179799",
    "user_id": "6001e1b4-662c-4ea7-ac74-c4ad74aeb52f",
    "name": "Malzeme Alımı",
    "type": "expense",
    "color": "#dc2626",
    "icon": "Package",
    "is_default": true,
    "is_active": true,
    "created_at": "2026-01-23T22:16:16.214Z",
    "updated_at": "2026-01-23T22:16:16.214Z",
    "deleted_at": null,
    "expense_type": null,
    "default_channel_id": null,
    "service_commission_rate": "0.00",
    "courier_service_rate": "0.00"
  },
  {
    "id": "a4bc3317-583d-4395-8f39-d2a6123f5795",
    "user_id": "6001e1b4-662c-4ea7-ac74-c4ad74aeb52f",
    "name": "Diğer Giderler",
    "type": "expense",
    "color": "#dc2626",
    "icon": "MoreHorizontal",
    "is_default": true,
    "is_active": true,
    "created_at": "2026-01-23T22:16:16.214Z",
    "updated_at": "2026-01-23T22:16:16.214Z",
    "deleted_at": null,
    "expense_type": null,
    "default_channel_id": null,
    "service_commission_rate": "0.00",
    "courier_service_rate": "0.00"
  },
  {
    "id": "6c88cd83-a1c6-4586-91fd-81d8e67bcf8d",
    "user_id": "edd5aac7-a093-4160-8162-685c6b782dae",
    "name": "Genel Satış",
    "type": "income",
    "color": "#16a34a",
    "icon": "ShoppingCart",
    "is_default": true,
    "is_active": true,
    "created_at": "2026-01-23T22:24:26.017Z",
    "updated_at": "2026-01-23T22:24:26.017Z",
    "deleted_at": null,
    "expense_type": null,
    "default_channel_id": null,
    "service_commission_rate": "0.00",
    "courier_service_rate": "0.00"
  },
  {
    "id": "04b12023-b6f7-48d8-b40a-0df87ee7bd13",
    "user_id": "edd5aac7-a093-4160-8162-685c6b782dae",
    "name": "Hizmet Geliri",
    "type": "income",
    "color": "#16a34a",
    "icon": "Briefcase",
    "is_default": true,
    "is_active": true,
    "created_at": "2026-01-23T22:24:26.019Z",
    "updated_at": "2026-01-23T22:24:26.019Z",
    "deleted_at": null,
    "expense_type": null,
    "default_channel_id": null,
    "service_commission_rate": "0.00",
    "courier_service_rate": "0.00"
  },
  {
    "id": "08ecc9a8-39c4-4e65-a7bd-f859aa490be4",
    "user_id": "edd5aac7-a093-4160-8162-685c6b782dae",
    "name": "Kira",
    "type": "expense",
    "color": "#dc2626",
    "icon": "Home",
    "is_default": true,
    "is_active": true,
    "created_at": "2026-01-23T22:24:26.019Z",
    "updated_at": "2026-01-23T22:24:26.019Z",
    "deleted_at": null,
    "expense_type": null,
    "default_channel_id": null,
    "service_commission_rate": "0.00",
    "courier_service_rate": "0.00"
  },
  {
    "id": "abf39f13-98e4-4750-a219-476648a194e1",
    "user_id": "edd5aac7-a093-4160-8162-685c6b782dae",
    "name": "Fatura (Elektrik/Su)",
    "type": "expense",
    "color": "#dc2626",
    "icon": "Zap",
    "is_default": true,
    "is_active": true,
    "created_at": "2026-01-23T22:24:26.020Z",
    "updated_at": "2026-01-23T22:24:26.020Z",
    "deleted_at": null,
    "expense_type": null,
    "default_channel_id": null,
    "service_commission_rate": "0.00",
    "courier_service_rate": "0.00"
  },
  {
    "id": "92ed966a-f0f6-4e93-8150-6610d9d1e494",
    "user_id": "edd5aac7-a093-4160-8162-685c6b782dae",
    "name": "Personel Maaşı",
    "type": "expense",
    "color": "#dc2626",
    "icon": "Users",
    "is_default": true,
    "is_active": true,
    "created_at": "2026-01-23T22:24:26.020Z",
    "updated_at": "2026-01-23T22:24:26.020Z",
    "deleted_at": null,
    "expense_type": null,
    "default_channel_id": null,
    "service_commission_rate": "0.00",
    "courier_service_rate": "0.00"
  },
  {
    "id": "b9231ee7-8cea-4198-8702-8ca9307a5747",
    "user_id": "edd5aac7-a093-4160-8162-685c6b782dae",
    "name": "Malzeme Alımı",
    "type": "expense",
    "color": "#dc2626",
    "icon": "Package",
    "is_default": true,
    "is_active": true,
    "created_at": "2026-01-23T22:24:26.021Z",
    "updated_at": "2026-01-23T22:24:26.021Z",
    "deleted_at": null,
    "expense_type": null,
    "default_channel_id": null,
    "service_commission_rate": "0.00",
    "courier_service_rate": "0.00"
  },
  {
    "id": "63bc9c1c-f578-4589-b750-4e86b68c1f2c",
    "user_id": "edd5aac7-a093-4160-8162-685c6b782dae",
    "name": "Diğer Giderler",
    "type": "expense",
    "color": "#dc2626",
    "icon": "MoreHorizontal",
    "is_default": true,
    "is_active": true,
    "created_at": "2026-01-23T22:24:26.021Z",
    "updated_at": "2026-01-23T22:24:26.021Z",
    "deleted_at": null,
    "expense_type": null,
    "default_channel_id": null,
    "service_commission_rate": "0.00",
    "courier_service_rate": "0.00"
  },
  {
    "id": "9804a45b-3aa0-48ab-8451-8a9fcd0a8999",
    "user_id": "dea0631c-e50f-4b63-b124-f64e5091f890",
    "name": "Genel Satış",
    "type": "income",
    "color": "#16a34a",
    "icon": "ShoppingCart",
    "is_default": true,
    "is_active": true,
    "created_at": "2026-01-23T22:24:26.097Z",
    "updated_at": "2026-01-23T22:24:26.097Z",
    "deleted_at": null,
    "expense_type": null,
    "default_channel_id": null,
    "service_commission_rate": "0.00",
    "courier_service_rate": "0.00"
  },
  {
    "id": "a9509658-7bde-4ef0-b518-8d59fce85648",
    "user_id": "dea0631c-e50f-4b63-b124-f64e5091f890",
    "name": "Hizmet Geliri",
    "type": "income",
    "color": "#16a34a",
    "icon": "Briefcase",
    "is_default": true,
    "is_active": true,
    "created_at": "2026-01-23T22:24:26.098Z",
    "updated_at": "2026-01-23T22:24:26.098Z",
    "deleted_at": null,
    "expense_type": null,
    "default_channel_id": null,
    "service_commission_rate": "0.00",
    "courier_service_rate": "0.00"
  },
  {
    "id": "1d7c3c4b-a108-44b7-a6f8-9c1b235c8c6b",
    "user_id": "dea0631c-e50f-4b63-b124-f64e5091f890",
    "name": "Kira",
    "type": "expense",
    "color": "#dc2626",
    "icon": "Home",
    "is_default": true,
    "is_active": true,
    "created_at": "2026-01-23T22:24:26.098Z",
    "updated_at": "2026-01-23T22:24:26.098Z",
    "deleted_at": null,
    "expense_type": null,
    "default_channel_id": null,
    "service_commission_rate": "0.00",
    "courier_service_rate": "0.00"
  },
  {
    "id": "2db582c3-f1f8-4d09-8735-cfc5d2a2a748",
    "user_id": "dea0631c-e50f-4b63-b124-f64e5091f890",
    "name": "Fatura (Elektrik/Su)",
    "type": "expense",
    "color": "#dc2626",
    "icon": "Zap",
    "is_default": true,
    "is_active": true,
    "created_at": "2026-01-23T22:24:26.099Z",
    "updated_at": "2026-01-23T22:24:26.099Z",
    "deleted_at": null,
    "expense_type": null,
    "default_channel_id": null,
    "service_commission_rate": "0.00",
    "courier_service_rate": "0.00"
  },
  {
    "id": "9a20b58a-4f44-436d-b8b7-198800c9269d",
    "user_id": "dea0631c-e50f-4b63-b124-f64e5091f890",
    "name": "Personel Maaşı",
    "type": "expense",
    "color": "#dc2626",
    "icon": "Users",
    "is_default": true,
    "is_active": true,
    "created_at": "2026-01-23T22:24:26.100Z",
    "updated_at": "2026-01-23T22:24:26.100Z",
    "deleted_at": null,
    "expense_type": null,
    "default_channel_id": null,
    "service_commission_rate": "0.00",
    "courier_service_rate": "0.00"
  },
  {
    "id": "ca4da627-5635-49e1-bdd7-bf1087f803f1",
    "user_id": "dea0631c-e50f-4b63-b124-f64e5091f890",
    "name": "Malzeme Alımı",
    "type": "expense",
    "color": "#dc2626",
    "icon": "Package",
    "is_default": true,
    "is_active": true,
    "created_at": "2026-01-23T22:24:26.100Z",
    "updated_at": "2026-01-23T22:24:26.100Z",
    "deleted_at": null,
    "expense_type": null,
    "default_channel_id": null,
    "service_commission_rate": "0.00",
    "courier_service_rate": "0.00"
  },
  {
    "id": "90747552-81ae-4f48-9acc-3c2b5396e279",
    "user_id": "dea0631c-e50f-4b63-b124-f64e5091f890",
    "name": "Diğer Giderler",
    "type": "expense",
    "color": "#dc2626",
    "icon": "MoreHorizontal",
    "is_default": true,
    "is_active": true,
    "created_at": "2026-01-23T22:24:26.101Z",
    "updated_at": "2026-01-23T22:24:26.101Z",
    "deleted_at": null,
    "expense_type": null,
    "default_channel_id": null,
    "service_commission_rate": "0.00",
    "courier_service_rate": "0.00"
  },
  {
    "id": "76d69ba8-1091-490d-9ca7-040aa2a12953",
    "user_id": "bc93c3fb-4927-4b9f-97b4-3575ca4d1d18",
    "name": "Genel Satış",
    "type": "income",
    "color": "#16a34a",
    "icon": "ShoppingCart",
    "is_default": true,
    "is_active": true,
    "created_at": "2026-01-23T22:24:54.463Z",
    "updated_at": "2026-01-23T22:24:54.463Z",
    "deleted_at": null,
    "expense_type": null,
    "default_channel_id": null,
    "service_commission_rate": "0.00",
    "courier_service_rate": "0.00"
  },
  {
    "id": "663ae491-e8b1-4093-bfdd-74ad7169c671",
    "user_id": "bc93c3fb-4927-4b9f-97b4-3575ca4d1d18",
    "name": "Hizmet Geliri",
    "type": "income",
    "color": "#16a34a",
    "icon": "Briefcase",
    "is_default": true,
    "is_active": true,
    "created_at": "2026-01-23T22:24:54.466Z",
    "updated_at": "2026-01-23T22:24:54.466Z",
    "deleted_at": null,
    "expense_type": null,
    "default_channel_id": null,
    "service_commission_rate": "0.00",
    "courier_service_rate": "0.00"
  },
  {
    "id": "cabda828-2a0e-418a-b614-b1c37a44f91d",
    "user_id": "bc93c3fb-4927-4b9f-97b4-3575ca4d1d18",
    "name": "Kira",
    "type": "expense",
    "color": "#dc2626",
    "icon": "Home",
    "is_default": true,
    "is_active": true,
    "created_at": "2026-01-23T22:24:54.467Z",
    "updated_at": "2026-01-23T22:24:54.467Z",
    "deleted_at": null,
    "expense_type": null,
    "default_channel_id": null,
    "service_commission_rate": "0.00",
    "courier_service_rate": "0.00"
  },
  {
    "id": "53d52a47-bf88-43b4-8e3a-ccda12d66443",
    "user_id": "bc93c3fb-4927-4b9f-97b4-3575ca4d1d18",
    "name": "Fatura (Elektrik/Su)",
    "type": "expense",
    "color": "#dc2626",
    "icon": "Zap",
    "is_default": true,
    "is_active": true,
    "created_at": "2026-01-23T22:24:54.467Z",
    "updated_at": "2026-01-23T22:24:54.467Z",
    "deleted_at": null,
    "expense_type": null,
    "default_channel_id": null,
    "service_commission_rate": "0.00",
    "courier_service_rate": "0.00"
  },
  {
    "id": "cce6d61a-cd48-4cf5-92e9-62f218d0aed7",
    "user_id": "bc93c3fb-4927-4b9f-97b4-3575ca4d1d18",
    "name": "Personel Maaşı",
    "type": "expense",
    "color": "#dc2626",
    "icon": "Users",
    "is_default": true,
    "is_active": true,
    "created_at": "2026-01-23T22:24:54.468Z",
    "updated_at": "2026-01-23T22:24:54.468Z",
    "deleted_at": null,
    "expense_type": null,
    "default_channel_id": null,
    "service_commission_rate": "0.00",
    "courier_service_rate": "0.00"
  },
  {
    "id": "ddf3e031-1c06-4c48-84d4-f76417c346cd",
    "user_id": "bc93c3fb-4927-4b9f-97b4-3575ca4d1d18",
    "name": "Malzeme Alımı",
    "type": "expense",
    "color": "#dc2626",
    "icon": "Package",
    "is_default": true,
    "is_active": true,
    "created_at": "2026-01-23T22:24:54.469Z",
    "updated_at": "2026-01-23T22:24:54.469Z",
    "deleted_at": null,
    "expense_type": null,
    "default_channel_id": null,
    "service_commission_rate": "0.00",
    "courier_service_rate": "0.00"
  },
  {
    "id": "c488ec68-69bd-402c-b164-f5040f40a578",
    "user_id": "bc93c3fb-4927-4b9f-97b4-3575ca4d1d18",
    "name": "Diğer Giderler",
    "type": "expense",
    "color": "#dc2626",
    "icon": "MoreHorizontal",
    "is_default": true,
    "is_active": true,
    "created_at": "2026-01-23T22:24:54.469Z",
    "updated_at": "2026-01-23T22:24:54.469Z",
    "deleted_at": null,
    "expense_type": null,
    "default_channel_id": null,
    "service_commission_rate": "0.00",
    "courier_service_rate": "0.00"
  },
  {
    "id": "d2fc01e7-2bac-424c-be28-20ea03c9d0d0",
    "user_id": "a1a8bcd4-0376-45ba-a264-ca89e3901397",
    "name": "Genel Satış",
    "type": "income",
    "color": "#16a34a",
    "icon": "ShoppingCart",
    "is_default": true,
    "is_active": true,
    "created_at": "2026-01-23T22:24:54.542Z",
    "updated_at": "2026-01-23T22:24:54.542Z",
    "deleted_at": null,
    "expense_type": null,
    "default_channel_id": null,
    "service_commission_rate": "0.00",
    "courier_service_rate": "0.00"
  },
  {
    "id": "3cc17611-df1e-4b64-804d-f49cc4023c5c",
    "user_id": "a1a8bcd4-0376-45ba-a264-ca89e3901397",
    "name": "Hizmet Geliri",
    "type": "income",
    "color": "#16a34a",
    "icon": "Briefcase",
    "is_default": true,
    "is_active": true,
    "created_at": "2026-01-23T22:24:54.543Z",
    "updated_at": "2026-01-23T22:24:54.543Z",
    "deleted_at": null,
    "expense_type": null,
    "default_channel_id": null,
    "service_commission_rate": "0.00",
    "courier_service_rate": "0.00"
  },
  {
    "id": "f600fc92-d911-454b-88b8-0c3385d8ffd4",
    "user_id": "a1a8bcd4-0376-45ba-a264-ca89e3901397",
    "name": "Kira",
    "type": "expense",
    "color": "#dc2626",
    "icon": "Home",
    "is_default": true,
    "is_active": true,
    "created_at": "2026-01-23T22:24:54.543Z",
    "updated_at": "2026-01-23T22:24:54.543Z",
    "deleted_at": null,
    "expense_type": null,
    "default_channel_id": null,
    "service_commission_rate": "0.00",
    "courier_service_rate": "0.00"
  },
  {
    "id": "5d5dcf40-afc8-4c35-ad88-70148125bf0d",
    "user_id": "a1a8bcd4-0376-45ba-a264-ca89e3901397",
    "name": "Fatura (Elektrik/Su)",
    "type": "expense",
    "color": "#dc2626",
    "icon": "Zap",
    "is_default": true,
    "is_active": true,
    "created_at": "2026-01-23T22:24:54.544Z",
    "updated_at": "2026-01-23T22:24:54.544Z",
    "deleted_at": null,
    "expense_type": null,
    "default_channel_id": null,
    "service_commission_rate": "0.00",
    "courier_service_rate": "0.00"
  },
  {
    "id": "11ce3456-20e4-422c-940f-3065bcb3402e",
    "user_id": "a1a8bcd4-0376-45ba-a264-ca89e3901397",
    "name": "Personel Maaşı",
    "type": "expense",
    "color": "#dc2626",
    "icon": "Users",
    "is_default": true,
    "is_active": true,
    "created_at": "2026-01-23T22:24:54.544Z",
    "updated_at": "2026-01-23T22:24:54.544Z",
    "deleted_at": null,
    "expense_type": null,
    "default_channel_id": null,
    "service_commission_rate": "0.00",
    "courier_service_rate": "0.00"
  },
  {
    "id": "59626438-c776-4f29-98b0-2a0d982a3141",
    "user_id": "a1a8bcd4-0376-45ba-a264-ca89e3901397",
    "name": "Malzeme Alımı",
    "type": "expense",
    "color": "#dc2626",
    "icon": "Package",
    "is_default": true,
    "is_active": true,
    "created_at": "2026-01-23T22:24:54.545Z",
    "updated_at": "2026-01-23T22:24:54.545Z",
    "deleted_at": null,
    "expense_type": null,
    "default_channel_id": null,
    "service_commission_rate": "0.00",
    "courier_service_rate": "0.00"
  },
  {
    "id": "a382646e-3f2f-478e-beb0-dee1502834a7",
    "user_id": "a1a8bcd4-0376-45ba-a264-ca89e3901397",
    "name": "Diğer Giderler",
    "type": "expense",
    "color": "#dc2626",
    "icon": "MoreHorizontal",
    "is_default": true,
    "is_active": true,
    "created_at": "2026-01-23T22:24:54.546Z",
    "updated_at": "2026-01-23T22:24:54.546Z",
    "deleted_at": null,
    "expense_type": null,
    "default_channel_id": null,
    "service_commission_rate": "0.00",
    "courier_service_rate": "0.00"
  },
  {
    "id": "e4c8ff0a-dd8e-42a0-9d50-84b4ccbda05f",
    "user_id": "28caee79-254e-459b-a91f-ebeb09d6ff49",
    "name": "Genel Satış",
    "type": "income",
    "color": "#16a34a",
    "icon": "ShoppingCart",
    "is_default": true,
    "is_active": true,
    "created_at": "2026-01-23T22:25:37.474Z",
    "updated_at": "2026-01-23T22:25:37.474Z",
    "deleted_at": null,
    "expense_type": null,
    "default_channel_id": null,
    "service_commission_rate": "0.00",
    "courier_service_rate": "0.00"
  },
  {
    "id": "8e357479-9fb1-4f55-8c84-70cfdc13bbc3",
    "user_id": "28caee79-254e-459b-a91f-ebeb09d6ff49",
    "name": "Hizmet Geliri",
    "type": "income",
    "color": "#16a34a",
    "icon": "Briefcase",
    "is_default": true,
    "is_active": true,
    "created_at": "2026-01-23T22:25:37.476Z",
    "updated_at": "2026-01-23T22:25:37.476Z",
    "deleted_at": null,
    "expense_type": null,
    "default_channel_id": null,
    "service_commission_rate": "0.00",
    "courier_service_rate": "0.00"
  },
  {
    "id": "c779c96c-554e-458d-9bb3-6e0ba449d1bc",
    "user_id": "28caee79-254e-459b-a91f-ebeb09d6ff49",
    "name": "Kira",
    "type": "expense",
    "color": "#dc2626",
    "icon": "Home",
    "is_default": true,
    "is_active": true,
    "created_at": "2026-01-23T22:25:37.477Z",
    "updated_at": "2026-01-23T22:25:37.477Z",
    "deleted_at": null,
    "expense_type": null,
    "default_channel_id": null,
    "service_commission_rate": "0.00",
    "courier_service_rate": "0.00"
  },
  {
    "id": "b1c6d721-cd55-439b-86d7-25908e192f3c",
    "user_id": "28caee79-254e-459b-a91f-ebeb09d6ff49",
    "name": "Fatura (Elektrik/Su)",
    "type": "expense",
    "color": "#dc2626",
    "icon": "Zap",
    "is_default": true,
    "is_active": true,
    "created_at": "2026-01-23T22:25:37.477Z",
    "updated_at": "2026-01-23T22:25:37.477Z",
    "deleted_at": null,
    "expense_type": null,
    "default_channel_id": null,
    "service_commission_rate": "0.00",
    "courier_service_rate": "0.00"
  },
  {
    "id": "2167553f-f53b-4ed1-a720-bb20e472a83c",
    "user_id": "28caee79-254e-459b-a91f-ebeb09d6ff49",
    "name": "Personel Maaşı",
    "type": "expense",
    "color": "#dc2626",
    "icon": "Users",
    "is_default": true,
    "is_active": true,
    "created_at": "2026-01-23T22:25:37.478Z",
    "updated_at": "2026-01-23T22:25:37.478Z",
    "deleted_at": null,
    "expense_type": null,
    "default_channel_id": null,
    "service_commission_rate": "0.00",
    "courier_service_rate": "0.00"
  },
  {
    "id": "cde99a26-c037-4a83-a67d-8fddd5ad59fb",
    "user_id": "28caee79-254e-459b-a91f-ebeb09d6ff49",
    "name": "Malzeme Alımı",
    "type": "expense",
    "color": "#dc2626",
    "icon": "Package",
    "is_default": true,
    "is_active": true,
    "created_at": "2026-01-23T22:25:37.479Z",
    "updated_at": "2026-01-23T22:25:37.479Z",
    "deleted_at": null,
    "expense_type": null,
    "default_channel_id": null,
    "service_commission_rate": "0.00",
    "courier_service_rate": "0.00"
  },
  {
    "id": "23a890ac-e365-46c5-8394-f04e013a340d",
    "user_id": "28caee79-254e-459b-a91f-ebeb09d6ff49",
    "name": "Diğer Giderler",
    "type": "expense",
    "color": "#dc2626",
    "icon": "MoreHorizontal",
    "is_default": true,
    "is_active": true,
    "created_at": "2026-01-23T22:25:37.479Z",
    "updated_at": "2026-01-23T22:25:37.479Z",
    "deleted_at": null,
    "expense_type": null,
    "default_channel_id": null,
    "service_commission_rate": "0.00",
    "courier_service_rate": "0.00"
  },
  {
    "id": "4c7ffa96-e9d4-4f0b-a26e-1a1634d2a183",
    "user_id": "445e602d-4197-443e-8745-808e663aeaf8",
    "name": "Genel Satış",
    "type": "income",
    "color": "#16a34a",
    "icon": "ShoppingCart",
    "is_default": true,
    "is_active": true,
    "created_at": "2026-01-23T22:25:37.557Z",
    "updated_at": "2026-01-23T22:25:37.557Z",
    "deleted_at": null,
    "expense_type": null,
    "default_channel_id": null,
    "service_commission_rate": "0.00",
    "courier_service_rate": "0.00"
  },
  {
    "id": "51d737a9-f726-4b31-be44-895e6a1a213c",
    "user_id": "445e602d-4197-443e-8745-808e663aeaf8",
    "name": "Hizmet Geliri",
    "type": "income",
    "color": "#16a34a",
    "icon": "Briefcase",
    "is_default": true,
    "is_active": true,
    "created_at": "2026-01-23T22:25:37.557Z",
    "updated_at": "2026-01-23T22:25:37.557Z",
    "deleted_at": null,
    "expense_type": null,
    "default_channel_id": null,
    "service_commission_rate": "0.00",
    "courier_service_rate": "0.00"
  },
  {
    "id": "1f349ec6-b561-4655-a48f-0a01c9816724",
    "user_id": "445e602d-4197-443e-8745-808e663aeaf8",
    "name": "Kira",
    "type": "expense",
    "color": "#dc2626",
    "icon": "Home",
    "is_default": true,
    "is_active": true,
    "created_at": "2026-01-23T22:25:37.558Z",
    "updated_at": "2026-01-23T22:25:37.558Z",
    "deleted_at": null,
    "expense_type": null,
    "default_channel_id": null,
    "service_commission_rate": "0.00",
    "courier_service_rate": "0.00"
  },
  {
    "id": "1599763c-1ce8-45ba-be24-8f06ecc2dc16",
    "user_id": "445e602d-4197-443e-8745-808e663aeaf8",
    "name": "Fatura (Elektrik/Su)",
    "type": "expense",
    "color": "#dc2626",
    "icon": "Zap",
    "is_default": true,
    "is_active": true,
    "created_at": "2026-01-23T22:25:37.559Z",
    "updated_at": "2026-01-23T22:25:37.559Z",
    "deleted_at": null,
    "expense_type": null,
    "default_channel_id": null,
    "service_commission_rate": "0.00",
    "courier_service_rate": "0.00"
  },
  {
    "id": "7b3de6b0-c157-487a-a992-23ad86f28cab",
    "user_id": "445e602d-4197-443e-8745-808e663aeaf8",
    "name": "Personel Maaşı",
    "type": "expense",
    "color": "#dc2626",
    "icon": "Users",
    "is_default": true,
    "is_active": true,
    "created_at": "2026-01-23T22:25:37.559Z",
    "updated_at": "2026-01-23T22:25:37.559Z",
    "deleted_at": null,
    "expense_type": null,
    "default_channel_id": null,
    "service_commission_rate": "0.00",
    "courier_service_rate": "0.00"
  },
  {
    "id": "62f3ffca-7734-45e0-921f-4848e1a74254",
    "user_id": "445e602d-4197-443e-8745-808e663aeaf8",
    "name": "Malzeme Alımı",
    "type": "expense",
    "color": "#dc2626",
    "icon": "Package",
    "is_default": true,
    "is_active": true,
    "created_at": "2026-01-23T22:25:37.559Z",
    "updated_at": "2026-01-23T22:25:37.559Z",
    "deleted_at": null,
    "expense_type": null,
    "default_channel_id": null,
    "service_commission_rate": "0.00",
    "courier_service_rate": "0.00"
  },
  {
    "id": "2d4a21c4-a87b-41c8-814e-b321bec0c760",
    "user_id": "445e602d-4197-443e-8745-808e663aeaf8",
    "name": "Diğer Giderler",
    "type": "expense",
    "color": "#dc2626",
    "icon": "MoreHorizontal",
    "is_default": true,
    "is_active": true,
    "created_at": "2026-01-23T22:25:37.560Z",
    "updated_at": "2026-01-23T22:25:37.560Z",
    "deleted_at": null,
    "expense_type": null,
    "default_channel_id": null,
    "service_commission_rate": "0.00",
    "courier_service_rate": "0.00"
  },
  {
    "id": "fb980eae-7a85-4a23-9da6-0e2be08de45d",
    "user_id": "b074d982-de1c-43f5-90bc-1d33ce13cca3",
    "name": "Genel Satış",
    "type": "income",
    "color": "#16a34a",
    "icon": "ShoppingCart",
    "is_default": true,
    "is_active": true,
    "created_at": "2026-01-23T22:30:21.939Z",
    "updated_at": "2026-01-23T22:30:21.939Z",
    "deleted_at": null,
    "expense_type": null,
    "default_channel_id": null,
    "service_commission_rate": "0.00",
    "courier_service_rate": "0.00"
  },
  {
    "id": "377d8a6b-0bd4-4ee6-9bce-f6db04ff27ff",
    "user_id": "b074d982-de1c-43f5-90bc-1d33ce13cca3",
    "name": "Hizmet Geliri",
    "type": "income",
    "color": "#16a34a",
    "icon": "Briefcase",
    "is_default": true,
    "is_active": true,
    "created_at": "2026-01-23T22:30:21.941Z",
    "updated_at": "2026-01-23T22:30:21.941Z",
    "deleted_at": null,
    "expense_type": null,
    "default_channel_id": null,
    "service_commission_rate": "0.00",
    "courier_service_rate": "0.00"
  },
  {
    "id": "fd23c29d-aa0b-47ef-bd75-d627e6e17f97",
    "user_id": "b074d982-de1c-43f5-90bc-1d33ce13cca3",
    "name": "Kira",
    "type": "expense",
    "color": "#dc2626",
    "icon": "Home",
    "is_default": true,
    "is_active": true,
    "created_at": "2026-01-23T22:30:21.941Z",
    "updated_at": "2026-01-23T22:30:21.941Z",
    "deleted_at": null,
    "expense_type": null,
    "default_channel_id": null,
    "service_commission_rate": "0.00",
    "courier_service_rate": "0.00"
  },
  {
    "id": "1512e7ca-5f1c-47f0-9105-e667eb8548f7",
    "user_id": "b074d982-de1c-43f5-90bc-1d33ce13cca3",
    "name": "Fatura (Elektrik/Su)",
    "type": "expense",
    "color": "#dc2626",
    "icon": "Zap",
    "is_default": true,
    "is_active": true,
    "created_at": "2026-01-23T22:30:21.942Z",
    "updated_at": "2026-01-23T22:30:21.942Z",
    "deleted_at": null,
    "expense_type": null,
    "default_channel_id": null,
    "service_commission_rate": "0.00",
    "courier_service_rate": "0.00"
  },
  {
    "id": "c0520fed-fa12-4942-a633-4eb2bf1d1d0b",
    "user_id": "b074d982-de1c-43f5-90bc-1d33ce13cca3",
    "name": "Personel Maaşı",
    "type": "expense",
    "color": "#dc2626",
    "icon": "Users",
    "is_default": true,
    "is_active": true,
    "created_at": "2026-01-23T22:30:21.942Z",
    "updated_at": "2026-01-23T22:30:21.942Z",
    "deleted_at": null,
    "expense_type": null,
    "default_channel_id": null,
    "service_commission_rate": "0.00",
    "courier_service_rate": "0.00"
  },
  {
    "id": "7bbebbe4-57f0-4d78-9691-8dae01a61573",
    "user_id": "b074d982-de1c-43f5-90bc-1d33ce13cca3",
    "name": "Malzeme Alımı",
    "type": "expense",
    "color": "#dc2626",
    "icon": "Package",
    "is_default": true,
    "is_active": true,
    "created_at": "2026-01-23T22:30:21.943Z",
    "updated_at": "2026-01-23T22:30:21.943Z",
    "deleted_at": null,
    "expense_type": null,
    "default_channel_id": null,
    "service_commission_rate": "0.00",
    "courier_service_rate": "0.00"
  },
  {
    "id": "8023a1e2-9e07-45f9-89ef-33bd42ff06fb",
    "user_id": "b074d982-de1c-43f5-90bc-1d33ce13cca3",
    "name": "Diğer Giderler",
    "type": "expense",
    "color": "#dc2626",
    "icon": "MoreHorizontal",
    "is_default": true,
    "is_active": true,
    "created_at": "2026-01-23T22:30:21.944Z",
    "updated_at": "2026-01-23T22:30:21.944Z",
    "deleted_at": null,
    "expense_type": null,
    "default_channel_id": null,
    "service_commission_rate": "0.00",
    "courier_service_rate": "0.00"
  },
  {
    "id": "23212ce0-8f1f-4928-a0dd-fed873a9fd03",
    "user_id": "284feb03-d06d-4381-bd73-d9b28f023629",
    "name": "Genel Satış",
    "type": "income",
    "color": "#16a34a",
    "icon": "ShoppingCart",
    "is_default": true,
    "is_active": true,
    "created_at": "2026-01-23T22:30:22.016Z",
    "updated_at": "2026-01-23T22:30:22.016Z",
    "deleted_at": null,
    "expense_type": null,
    "default_channel_id": null,
    "service_commission_rate": "0.00",
    "courier_service_rate": "0.00"
  },
  {
    "id": "6a53b188-dd29-40c0-9009-884c99d5e34f",
    "user_id": "284feb03-d06d-4381-bd73-d9b28f023629",
    "name": "Hizmet Geliri",
    "type": "income",
    "color": "#16a34a",
    "icon": "Briefcase",
    "is_default": true,
    "is_active": true,
    "created_at": "2026-01-23T22:30:22.017Z",
    "updated_at": "2026-01-23T22:30:22.017Z",
    "deleted_at": null,
    "expense_type": null,
    "default_channel_id": null,
    "service_commission_rate": "0.00",
    "courier_service_rate": "0.00"
  },
  {
    "id": "4de522f2-97aa-40d3-a578-7f7273a3e2d7",
    "user_id": "284feb03-d06d-4381-bd73-d9b28f023629",
    "name": "Kira",
    "type": "expense",
    "color": "#dc2626",
    "icon": "Home",
    "is_default": true,
    "is_active": true,
    "created_at": "2026-01-23T22:30:22.018Z",
    "updated_at": "2026-01-23T22:30:22.018Z",
    "deleted_at": null,
    "expense_type": null,
    "default_channel_id": null,
    "service_commission_rate": "0.00",
    "courier_service_rate": "0.00"
  },
  {
    "id": "c86b36cf-036b-46b2-82af-4830c3305aad",
    "user_id": "284feb03-d06d-4381-bd73-d9b28f023629",
    "name": "Fatura (Elektrik/Su)",
    "type": "expense",
    "color": "#dc2626",
    "icon": "Zap",
    "is_default": true,
    "is_active": true,
    "created_at": "2026-01-23T22:30:22.018Z",
    "updated_at": "2026-01-23T22:30:22.018Z",
    "deleted_at": null,
    "expense_type": null,
    "default_channel_id": null,
    "service_commission_rate": "0.00",
    "courier_service_rate": "0.00"
  },
  {
    "id": "ff956ef1-11ef-40e6-b0c3-23b27d2d182f",
    "user_id": "284feb03-d06d-4381-bd73-d9b28f023629",
    "name": "Personel Maaşı",
    "type": "expense",
    "color": "#dc2626",
    "icon": "Users",
    "is_default": true,
    "is_active": true,
    "created_at": "2026-01-23T22:30:22.018Z",
    "updated_at": "2026-01-23T22:30:22.018Z",
    "deleted_at": null,
    "expense_type": null,
    "default_channel_id": null,
    "service_commission_rate": "0.00",
    "courier_service_rate": "0.00"
  },
  {
    "id": "e4096110-55df-4c43-9b90-d40a0771b729",
    "user_id": "284feb03-d06d-4381-bd73-d9b28f023629",
    "name": "Malzeme Alımı",
    "type": "expense",
    "color": "#dc2626",
    "icon": "Package",
    "is_default": true,
    "is_active": true,
    "created_at": "2026-01-23T22:30:22.019Z",
    "updated_at": "2026-01-23T22:30:22.019Z",
    "deleted_at": null,
    "expense_type": null,
    "default_channel_id": null,
    "service_commission_rate": "0.00",
    "courier_service_rate": "0.00"
  },
  {
    "id": "844a1029-8d74-4505-ae7d-80a1508d3253",
    "user_id": "284feb03-d06d-4381-bd73-d9b28f023629",
    "name": "Diğer Giderler",
    "type": "expense",
    "color": "#dc2626",
    "icon": "MoreHorizontal",
    "is_default": true,
    "is_active": true,
    "created_at": "2026-01-23T22:30:22.019Z",
    "updated_at": "2026-01-23T22:30:22.019Z",
    "deleted_at": null,
    "expense_type": null,
    "default_channel_id": null,
    "service_commission_rate": "0.00",
    "courier_service_rate": "0.00"
  },
  {
    "id": "71704941-a39c-41a9-a660-369176ff952f",
    "user_id": "2449f7b1-59d3-475f-b62e-ed3f320f7875",
    "name": "Genel Satış",
    "type": "income",
    "color": "#16a34a",
    "icon": "ShoppingCart",
    "is_default": true,
    "is_active": true,
    "created_at": "2026-01-23T22:31:31.318Z",
    "updated_at": "2026-01-23T22:31:31.318Z",
    "deleted_at": null,
    "expense_type": null,
    "default_channel_id": null,
    "service_commission_rate": "0.00",
    "courier_service_rate": "0.00"
  },
  {
    "id": "66ed8a65-224f-4fa7-b4c6-5770ee7c11ed",
    "user_id": "2449f7b1-59d3-475f-b62e-ed3f320f7875",
    "name": "Hizmet Geliri",
    "type": "income",
    "color": "#16a34a",
    "icon": "Briefcase",
    "is_default": true,
    "is_active": true,
    "created_at": "2026-01-23T22:31:31.321Z",
    "updated_at": "2026-01-23T22:31:31.321Z",
    "deleted_at": null,
    "expense_type": null,
    "default_channel_id": null,
    "service_commission_rate": "0.00",
    "courier_service_rate": "0.00"
  },
  {
    "id": "0a2140a5-c65d-48bb-bfc2-2413aebcc461",
    "user_id": "2449f7b1-59d3-475f-b62e-ed3f320f7875",
    "name": "Kira",
    "type": "expense",
    "color": "#dc2626",
    "icon": "Home",
    "is_default": true,
    "is_active": true,
    "created_at": "2026-01-23T22:31:31.322Z",
    "updated_at": "2026-01-23T22:31:31.322Z",
    "deleted_at": null,
    "expense_type": null,
    "default_channel_id": null,
    "service_commission_rate": "0.00",
    "courier_service_rate": "0.00"
  },
  {
    "id": "430fad88-18cd-4535-a437-def7bc15139a",
    "user_id": "2449f7b1-59d3-475f-b62e-ed3f320f7875",
    "name": "Fatura (Elektrik/Su)",
    "type": "expense",
    "color": "#dc2626",
    "icon": "Zap",
    "is_default": true,
    "is_active": true,
    "created_at": "2026-01-23T22:31:31.322Z",
    "updated_at": "2026-01-23T22:31:31.322Z",
    "deleted_at": null,
    "expense_type": null,
    "default_channel_id": null,
    "service_commission_rate": "0.00",
    "courier_service_rate": "0.00"
  },
  {
    "id": "e41fa125-0950-4b02-bd42-d82229dbacc4",
    "user_id": "2449f7b1-59d3-475f-b62e-ed3f320f7875",
    "name": "Personel Maaşı",
    "type": "expense",
    "color": "#dc2626",
    "icon": "Users",
    "is_default": true,
    "is_active": true,
    "created_at": "2026-01-23T22:31:31.323Z",
    "updated_at": "2026-01-23T22:31:31.323Z",
    "deleted_at": null,
    "expense_type": null,
    "default_channel_id": null,
    "service_commission_rate": "0.00",
    "courier_service_rate": "0.00"
  },
  {
    "id": "9a28f09d-c25b-436b-81af-a8382a614f18",
    "user_id": "2449f7b1-59d3-475f-b62e-ed3f320f7875",
    "name": "Malzeme Alımı",
    "type": "expense",
    "color": "#dc2626",
    "icon": "Package",
    "is_default": true,
    "is_active": true,
    "created_at": "2026-01-23T22:31:31.324Z",
    "updated_at": "2026-01-23T22:31:31.324Z",
    "deleted_at": null,
    "expense_type": null,
    "default_channel_id": null,
    "service_commission_rate": "0.00",
    "courier_service_rate": "0.00"
  },
  {
    "id": "7ce1f90c-9c67-45e1-83ab-43be0c8957bb",
    "user_id": "2449f7b1-59d3-475f-b62e-ed3f320f7875",
    "name": "Diğer Giderler",
    "type": "expense",
    "color": "#dc2626",
    "icon": "MoreHorizontal",
    "is_default": true,
    "is_active": true,
    "created_at": "2026-01-23T22:31:31.325Z",
    "updated_at": "2026-01-23T22:31:31.325Z",
    "deleted_at": null,
    "expense_type": null,
    "default_channel_id": null,
    "service_commission_rate": "0.00",
    "courier_service_rate": "0.00"
  },
  {
    "id": "6fd39ed6-544d-4ba9-abde-9d1be575584e",
    "user_id": "6e0bfed8-76ec-42d1-8b68-b0b7339a5374",
    "name": "Genel Satış",
    "type": "income",
    "color": "#16a34a",
    "icon": "ShoppingCart",
    "is_default": true,
    "is_active": true,
    "created_at": "2026-01-23T22:31:31.398Z",
    "updated_at": "2026-01-23T22:31:31.398Z",
    "deleted_at": null,
    "expense_type": null,
    "default_channel_id": null,
    "service_commission_rate": "0.00",
    "courier_service_rate": "0.00"
  },
  {
    "id": "31778e04-fc53-459c-bc3b-1c50fff403c2",
    "user_id": "6e0bfed8-76ec-42d1-8b68-b0b7339a5374",
    "name": "Hizmet Geliri",
    "type": "income",
    "color": "#16a34a",
    "icon": "Briefcase",
    "is_default": true,
    "is_active": true,
    "created_at": "2026-01-23T22:31:31.399Z",
    "updated_at": "2026-01-23T22:31:31.399Z",
    "deleted_at": null,
    "expense_type": null,
    "default_channel_id": null,
    "service_commission_rate": "0.00",
    "courier_service_rate": "0.00"
  },
  {
    "id": "fd7a0585-037f-4ade-a8bb-6d33eb057bdf",
    "user_id": "6e0bfed8-76ec-42d1-8b68-b0b7339a5374",
    "name": "Kira",
    "type": "expense",
    "color": "#dc2626",
    "icon": "Home",
    "is_default": true,
    "is_active": true,
    "created_at": "2026-01-23T22:31:31.399Z",
    "updated_at": "2026-01-23T22:31:31.399Z",
    "deleted_at": null,
    "expense_type": null,
    "default_channel_id": null,
    "service_commission_rate": "0.00",
    "courier_service_rate": "0.00"
  },
  {
    "id": "be49d939-cbe6-4398-9efe-3905f2b5f54e",
    "user_id": "6e0bfed8-76ec-42d1-8b68-b0b7339a5374",
    "name": "Fatura (Elektrik/Su)",
    "type": "expense",
    "color": "#dc2626",
    "icon": "Zap",
    "is_default": true,
    "is_active": true,
    "created_at": "2026-01-23T22:31:31.400Z",
    "updated_at": "2026-01-23T22:31:31.400Z",
    "deleted_at": null,
    "expense_type": null,
    "default_channel_id": null,
    "service_commission_rate": "0.00",
    "courier_service_rate": "0.00"
  },
  {
    "id": "b33a5c97-c6f3-48e0-afab-422519642d38",
    "user_id": "6e0bfed8-76ec-42d1-8b68-b0b7339a5374",
    "name": "Personel Maaşı",
    "type": "expense",
    "color": "#dc2626",
    "icon": "Users",
    "is_default": true,
    "is_active": true,
    "created_at": "2026-01-23T22:31:31.400Z",
    "updated_at": "2026-01-23T22:31:31.400Z",
    "deleted_at": null,
    "expense_type": null,
    "default_channel_id": null,
    "service_commission_rate": "0.00",
    "courier_service_rate": "0.00"
  },
  {
    "id": "7778f470-0861-4227-8cd9-32c43185b424",
    "user_id": "6e0bfed8-76ec-42d1-8b68-b0b7339a5374",
    "name": "Malzeme Alımı",
    "type": "expense",
    "color": "#dc2626",
    "icon": "Package",
    "is_default": true,
    "is_active": true,
    "created_at": "2026-01-23T22:31:31.401Z",
    "updated_at": "2026-01-23T22:31:31.401Z",
    "deleted_at": null,
    "expense_type": null,
    "default_channel_id": null,
    "service_commission_rate": "0.00",
    "courier_service_rate": "0.00"
  },
  {
    "id": "a39e90fe-b2b5-4228-9651-c91a2d5734ce",
    "user_id": "6e0bfed8-76ec-42d1-8b68-b0b7339a5374",
    "name": "Diğer Giderler",
    "type": "expense",
    "color": "#dc2626",
    "icon": "MoreHorizontal",
    "is_default": true,
    "is_active": true,
    "created_at": "2026-01-23T22:31:31.401Z",
    "updated_at": "2026-01-23T22:31:31.401Z",
    "deleted_at": null,
    "expense_type": null,
    "default_channel_id": null,
    "service_commission_rate": "0.00",
    "courier_service_rate": "0.00"
  },
  {
    "id": "1a159b2b-dfbd-4d29-ae3c-1b4b039ec571",
    "user_id": "d24eaf75-108a-41d3-b24c-dcdcf4ce5d72",
    "name": "Genel Satış",
    "type": "income",
    "color": "#16a34a",
    "icon": "ShoppingCart",
    "is_default": true,
    "is_active": true,
    "created_at": "2026-01-23T22:32:27.669Z",
    "updated_at": "2026-01-23T22:32:27.669Z",
    "deleted_at": null,
    "expense_type": null,
    "default_channel_id": null,
    "service_commission_rate": "0.00",
    "courier_service_rate": "0.00"
  },
  {
    "id": "a3183c9b-eccd-4915-bef9-6c82419d8f2f",
    "user_id": "d24eaf75-108a-41d3-b24c-dcdcf4ce5d72",
    "name": "Hizmet Geliri",
    "type": "income",
    "color": "#16a34a",
    "icon": "Briefcase",
    "is_default": true,
    "is_active": true,
    "created_at": "2026-01-23T22:32:27.671Z",
    "updated_at": "2026-01-23T22:32:27.671Z",
    "deleted_at": null,
    "expense_type": null,
    "default_channel_id": null,
    "service_commission_rate": "0.00",
    "courier_service_rate": "0.00"
  },
  {
    "id": "9cda3a6c-82d2-4894-a46f-6e60bc1550ed",
    "user_id": "d24eaf75-108a-41d3-b24c-dcdcf4ce5d72",
    "name": "Kira",
    "type": "expense",
    "color": "#dc2626",
    "icon": "Home",
    "is_default": true,
    "is_active": true,
    "created_at": "2026-01-23T22:32:27.672Z",
    "updated_at": "2026-01-23T22:32:27.672Z",
    "deleted_at": null,
    "expense_type": null,
    "default_channel_id": null,
    "service_commission_rate": "0.00",
    "courier_service_rate": "0.00"
  },
  {
    "id": "35ed8d16-8258-45de-a72b-41d247e152ea",
    "user_id": "d24eaf75-108a-41d3-b24c-dcdcf4ce5d72",
    "name": "Fatura (Elektrik/Su)",
    "type": "expense",
    "color": "#dc2626",
    "icon": "Zap",
    "is_default": true,
    "is_active": true,
    "created_at": "2026-01-23T22:32:27.673Z",
    "updated_at": "2026-01-23T22:32:27.673Z",
    "deleted_at": null,
    "expense_type": null,
    "default_channel_id": null,
    "service_commission_rate": "0.00",
    "courier_service_rate": "0.00"
  },
  {
    "id": "711875ab-93fe-45a5-a1dc-87da4af662a2",
    "user_id": "d24eaf75-108a-41d3-b24c-dcdcf4ce5d72",
    "name": "Personel Maaşı",
    "type": "expense",
    "color": "#dc2626",
    "icon": "Users",
    "is_default": true,
    "is_active": true,
    "created_at": "2026-01-23T22:32:27.674Z",
    "updated_at": "2026-01-23T22:32:27.674Z",
    "deleted_at": null,
    "expense_type": null,
    "default_channel_id": null,
    "service_commission_rate": "0.00",
    "courier_service_rate": "0.00"
  },
  {
    "id": "96ac05d2-6847-4883-ae82-21d5b93cd53f",
    "user_id": "d24eaf75-108a-41d3-b24c-dcdcf4ce5d72",
    "name": "Malzeme Alımı",
    "type": "expense",
    "color": "#dc2626",
    "icon": "Package",
    "is_default": true,
    "is_active": true,
    "created_at": "2026-01-23T22:32:27.675Z",
    "updated_at": "2026-01-23T22:32:27.675Z",
    "deleted_at": null,
    "expense_type": null,
    "default_channel_id": null,
    "service_commission_rate": "0.00",
    "courier_service_rate": "0.00"
  },
  {
    "id": "5bccb881-ea79-412e-b275-24884a31340a",
    "user_id": "d24eaf75-108a-41d3-b24c-dcdcf4ce5d72",
    "name": "Diğer Giderler",
    "type": "expense",
    "color": "#dc2626",
    "icon": "MoreHorizontal",
    "is_default": true,
    "is_active": true,
    "created_at": "2026-01-23T22:32:27.676Z",
    "updated_at": "2026-01-23T22:32:27.676Z",
    "deleted_at": null,
    "expense_type": null,
    "default_channel_id": null,
    "service_commission_rate": "0.00",
    "courier_service_rate": "0.00"
  },
  {
    "id": "e5162e99-71a3-4e4a-9646-ccbcb6306261",
    "user_id": "f1b9df20-19ec-42bc-8adc-6afb778cd432",
    "name": "Genel Satış",
    "type": "income",
    "color": "#16a34a",
    "icon": "ShoppingCart",
    "is_default": true,
    "is_active": true,
    "created_at": "2026-01-23T22:32:27.747Z",
    "updated_at": "2026-01-23T22:32:27.747Z",
    "deleted_at": null,
    "expense_type": null,
    "default_channel_id": null,
    "service_commission_rate": "0.00",
    "courier_service_rate": "0.00"
  },
  {
    "id": "7e839330-e413-4c02-a446-df7adff6349a",
    "user_id": "f1b9df20-19ec-42bc-8adc-6afb778cd432",
    "name": "Hizmet Geliri",
    "type": "income",
    "color": "#16a34a",
    "icon": "Briefcase",
    "is_default": true,
    "is_active": true,
    "created_at": "2026-01-23T22:32:27.748Z",
    "updated_at": "2026-01-23T22:32:27.748Z",
    "deleted_at": null,
    "expense_type": null,
    "default_channel_id": null,
    "service_commission_rate": "0.00",
    "courier_service_rate": "0.00"
  },
  {
    "id": "6b5696a8-7cad-4107-b511-01667281ebca",
    "user_id": "f1b9df20-19ec-42bc-8adc-6afb778cd432",
    "name": "Kira",
    "type": "expense",
    "color": "#dc2626",
    "icon": "Home",
    "is_default": true,
    "is_active": true,
    "created_at": "2026-01-23T22:32:27.748Z",
    "updated_at": "2026-01-23T22:32:27.748Z",
    "deleted_at": null,
    "expense_type": null,
    "default_channel_id": null,
    "service_commission_rate": "0.00",
    "courier_service_rate": "0.00"
  },
  {
    "id": "7807ed4c-eed5-49dd-b228-06b1de959a9b",
    "user_id": "f1b9df20-19ec-42bc-8adc-6afb778cd432",
    "name": "Fatura (Elektrik/Su)",
    "type": "expense",
    "color": "#dc2626",
    "icon": "Zap",
    "is_default": true,
    "is_active": true,
    "created_at": "2026-01-23T22:32:27.749Z",
    "updated_at": "2026-01-23T22:32:27.749Z",
    "deleted_at": null,
    "expense_type": null,
    "default_channel_id": null,
    "service_commission_rate": "0.00",
    "courier_service_rate": "0.00"
  },
  {
    "id": "01c189fc-a6e9-430e-b7f2-1bc542da3dfc",
    "user_id": "f1b9df20-19ec-42bc-8adc-6afb778cd432",
    "name": "Personel Maaşı",
    "type": "expense",
    "color": "#dc2626",
    "icon": "Users",
    "is_default": true,
    "is_active": true,
    "created_at": "2026-01-23T22:32:27.749Z",
    "updated_at": "2026-01-23T22:32:27.749Z",
    "deleted_at": null,
    "expense_type": null,
    "default_channel_id": null,
    "service_commission_rate": "0.00",
    "courier_service_rate": "0.00"
  },
  {
    "id": "02e29eb7-004b-4a4e-9ef2-a63907255d98",
    "user_id": "f1b9df20-19ec-42bc-8adc-6afb778cd432",
    "name": "Malzeme Alımı",
    "type": "expense",
    "color": "#dc2626",
    "icon": "Package",
    "is_default": true,
    "is_active": true,
    "created_at": "2026-01-23T22:32:27.750Z",
    "updated_at": "2026-01-23T22:32:27.750Z",
    "deleted_at": null,
    "expense_type": null,
    "default_channel_id": null,
    "service_commission_rate": "0.00",
    "courier_service_rate": "0.00"
  },
  {
    "id": "406a004e-cb5e-4c3c-be96-179bc2a5b322",
    "user_id": "f1b9df20-19ec-42bc-8adc-6afb778cd432",
    "name": "Diğer Giderler",
    "type": "expense",
    "color": "#dc2626",
    "icon": "MoreHorizontal",
    "is_default": true,
    "is_active": true,
    "created_at": "2026-01-23T22:32:27.750Z",
    "updated_at": "2026-01-23T22:32:27.750Z",
    "deleted_at": null,
    "expense_type": null,
    "default_channel_id": null,
    "service_commission_rate": "0.00",
    "courier_service_rate": "0.00"
  },
  {
    "id": "bbd8c3bb-bfd1-499f-8874-919574c9c1e2",
    "user_id": "c958f224-b1be-46b0-a975-078d3b231e2b",
    "name": "Genel Satış",
    "type": "income",
    "color": "#16a34a",
    "icon": "ShoppingCart",
    "is_default": true,
    "is_active": true,
    "created_at": "2026-01-23T22:38:35.190Z",
    "updated_at": "2026-01-23T22:38:35.190Z",
    "deleted_at": null,
    "expense_type": null,
    "default_channel_id": null,
    "service_commission_rate": "0.00",
    "courier_service_rate": "0.00"
  },
  {
    "id": "50cf11de-9a9d-4185-9932-a4750d064a47",
    "user_id": "c958f224-b1be-46b0-a975-078d3b231e2b",
    "name": "Hizmet Geliri",
    "type": "income",
    "color": "#16a34a",
    "icon": "Briefcase",
    "is_default": true,
    "is_active": true,
    "created_at": "2026-01-23T22:38:35.192Z",
    "updated_at": "2026-01-23T22:38:35.192Z",
    "deleted_at": null,
    "expense_type": null,
    "default_channel_id": null,
    "service_commission_rate": "0.00",
    "courier_service_rate": "0.00"
  },
  {
    "id": "0cfb8ee7-84ae-4f2c-8afa-99146660d002",
    "user_id": "c958f224-b1be-46b0-a975-078d3b231e2b",
    "name": "Kira",
    "type": "expense",
    "color": "#dc2626",
    "icon": "Home",
    "is_default": true,
    "is_active": true,
    "created_at": "2026-01-23T22:38:35.193Z",
    "updated_at": "2026-01-23T22:38:35.193Z",
    "deleted_at": null,
    "expense_type": null,
    "default_channel_id": null,
    "service_commission_rate": "0.00",
    "courier_service_rate": "0.00"
  },
  {
    "id": "7916a517-06d2-495c-a3ce-b5fe03a41aa8",
    "user_id": "c958f224-b1be-46b0-a975-078d3b231e2b",
    "name": "Fatura (Elektrik/Su)",
    "type": "expense",
    "color": "#dc2626",
    "icon": "Zap",
    "is_default": true,
    "is_active": true,
    "created_at": "2026-01-23T22:38:35.194Z",
    "updated_at": "2026-01-23T22:38:35.194Z",
    "deleted_at": null,
    "expense_type": null,
    "default_channel_id": null,
    "service_commission_rate": "0.00",
    "courier_service_rate": "0.00"
  },
  {
    "id": "777b059f-37e9-4e51-b9bb-f7282e53f8c0",
    "user_id": "c958f224-b1be-46b0-a975-078d3b231e2b",
    "name": "Personel Maaşı",
    "type": "expense",
    "color": "#dc2626",
    "icon": "Users",
    "is_default": true,
    "is_active": true,
    "created_at": "2026-01-23T22:38:35.195Z",
    "updated_at": "2026-01-23T22:38:35.195Z",
    "deleted_at": null,
    "expense_type": null,
    "default_channel_id": null,
    "service_commission_rate": "0.00",
    "courier_service_rate": "0.00"
  },
  {
    "id": "2bef7c6b-9946-4270-a4dd-ad4e371fc682",
    "user_id": "c958f224-b1be-46b0-a975-078d3b231e2b",
    "name": "Malzeme Alımı",
    "type": "expense",
    "color": "#dc2626",
    "icon": "Package",
    "is_default": true,
    "is_active": true,
    "created_at": "2026-01-23T22:38:35.196Z",
    "updated_at": "2026-01-23T22:38:35.196Z",
    "deleted_at": null,
    "expense_type": null,
    "default_channel_id": null,
    "service_commission_rate": "0.00",
    "courier_service_rate": "0.00"
  },
  {
    "id": "1553142b-6e8b-4095-9167-c3561107fe83",
    "user_id": "c958f224-b1be-46b0-a975-078d3b231e2b",
    "name": "Diğer Giderler",
    "type": "expense",
    "color": "#dc2626",
    "icon": "MoreHorizontal",
    "is_default": true,
    "is_active": true,
    "created_at": "2026-01-23T22:38:35.197Z",
    "updated_at": "2026-01-23T22:38:35.197Z",
    "deleted_at": null,
    "expense_type": null,
    "default_channel_id": null,
    "service_commission_rate": "0.00",
    "courier_service_rate": "0.00"
  },
  {
    "id": "df7cb357-7f74-4e01-b25c-f093f06a0f7f",
    "user_id": "be8b8541-f427-4287-a00b-a0e9783e5209",
    "name": "Kira",
    "type": "expense",
    "color": "#f43f5e",
    "icon": null,
    "is_default": false,
    "is_active": true,
    "created_at": "2026-01-23T23:00:29.942Z",
    "updated_at": "2026-01-24T11:48:42.222Z",
    "deleted_at": null,
    "expense_type": "fixed",
    "default_channel_id": null,
    "service_commission_rate": "0.00",
    "courier_service_rate": "0.00"
  },
  {
    "id": "ec3d3430-4ff3-43b8-9267-77db9b2c03d9",
    "user_id": "be8b8541-f427-4287-a00b-a0e9783e5209",
    "name": "Market",
    "type": "expense",
    "color": "#10b981",
    "icon": null,
    "is_default": false,
    "is_active": true,
    "created_at": "2026-01-24T07:41:35.309Z",
    "updated_at": "2026-01-24T11:48:50.785Z",
    "deleted_at": null,
    "expense_type": "operational",
    "default_channel_id": null,
    "service_commission_rate": "0.00",
    "courier_service_rate": "0.00"
  },
  {
    "id": "d13142d0-ac10-4a28-a3f6-3aba86d8de77",
    "user_id": "be8b8541-f427-4287-a00b-a0e9783e5209",
    "name": "TrendYol",
    "type": "income",
    "color": "#f97316",
    "icon": null,
    "is_default": false,
    "is_active": true,
    "created_at": "2026-01-23T23:01:00.207Z",
    "updated_at": "2026-01-30T22:51:35.114Z",
    "deleted_at": null,
    "expense_type": null,
    "default_channel_id": "305e0b20-dd98-4bde-942f-a1bc0a22e752",
    "service_commission_rate": "0.00",
    "courier_service_rate": "0.00"
  },
  {
    "id": "6612bef2-edfa-4f14-acc9-14062d7e0b36",
    "user_id": "be8b8541-f427-4287-a00b-a0e9783e5209",
    "name": "Elektrik",
    "type": "expense",
    "color": "#f97316",
    "icon": null,
    "is_default": false,
    "is_active": true,
    "created_at": "2026-01-23T23:00:22.259Z",
    "updated_at": "2026-01-24T11:48:31.347Z",
    "deleted_at": null,
    "expense_type": "fixed",
    "default_channel_id": null,
    "service_commission_rate": "0.00",
    "courier_service_rate": "0.00"
  },
  {
    "id": "e81262f3-6d07-4cae-a227-7abfb64a4d9b",
    "user_id": "be8b8541-f427-4287-a00b-a0e9783e5209",
    "name": "Vergi",
    "type": "expense",
    "color": "#6366f1",
    "icon": null,
    "is_default": false,
    "is_active": true,
    "created_at": "2026-01-23T23:00:06.248Z",
    "updated_at": "2026-01-24T11:48:59.152Z",
    "deleted_at": null,
    "expense_type": "fixed",
    "default_channel_id": null,
    "service_commission_rate": "0.00",
    "courier_service_rate": "0.00"
  },
  {
    "id": "c94f97c8-228c-4383-a096-5e1479b930f7",
    "user_id": "be8b8541-f427-4287-a00b-a0e9783e5209",
    "name": "Yemek Sepeti",
    "type": "income",
    "color": "#f43f5e",
    "icon": null,
    "is_default": false,
    "is_active": true,
    "created_at": "2026-01-24T07:08:53.369Z",
    "updated_at": "2026-02-10T18:30:54.290Z",
    "deleted_at": null,
    "expense_type": null,
    "default_channel_id": "305e0b20-dd98-4bde-942f-a1bc0a22e752",
    "service_commission_rate": "5.00",
    "courier_service_rate": "5.00"
  },
  {
    "id": "2a35ae13-e12c-4f73-aa0c-eec79d86f811",
    "user_id": "be8b8541-f427-4287-a00b-a0e9783e5209",
    "name": "Getir",
    "type": "income",
    "color": "#8b5cf6",
    "icon": null,
    "is_default": false,
    "is_active": true,
    "created_at": "2026-01-23T23:00:44.038Z",
    "updated_at": "2026-02-09T20:23:27.384Z",
    "deleted_at": null,
    "expense_type": null,
    "default_channel_id": "305e0b20-dd98-4bde-942f-a1bc0a22e752",
    "service_commission_rate": "10.00",
    "courier_service_rate": "0.00"
  },
  {
    "id": "872ad2d1-c781-4872-8b19-13a4e5673867",
    "user_id": "be8b8541-f427-4287-a00b-a0e9783e5209",
    "name": "Ağırlama",
    "type": "expense",
    "color": "#06b6d4",
    "icon": null,
    "is_default": false,
    "is_active": true,
    "created_at": "2026-01-24T11:50:09.684Z",
    "updated_at": "2026-01-24T11:50:18.468Z",
    "deleted_at": null,
    "expense_type": "personal",
    "default_channel_id": null,
    "service_commission_rate": "0.00",
    "courier_service_rate": "0.00"
  },
  {
    "id": "d4ef7c7a-99e3-45aa-917a-350dd1ce08ee",
    "user_id": "d4b5a038-dab9-4b00-8fdf-cbcde292cc94",
    "name": "Genel Satış",
    "type": "income",
    "color": "#16a34a",
    "icon": "ShoppingCart",
    "is_default": true,
    "is_active": true,
    "created_at": "2026-01-26T08:58:59.646Z",
    "updated_at": "2026-01-26T08:58:59.646Z",
    "deleted_at": null,
    "expense_type": null,
    "default_channel_id": null,
    "service_commission_rate": "0.00",
    "courier_service_rate": "0.00"
  },
  {
    "id": "f5c3848e-4b53-4b90-bee9-795157444a82",
    "user_id": "d4b5a038-dab9-4b00-8fdf-cbcde292cc94",
    "name": "Hizmet Geliri",
    "type": "income",
    "color": "#16a34a",
    "icon": "Briefcase",
    "is_default": true,
    "is_active": true,
    "created_at": "2026-01-26T08:58:59.649Z",
    "updated_at": "2026-01-26T08:58:59.649Z",
    "deleted_at": null,
    "expense_type": null,
    "default_channel_id": null,
    "service_commission_rate": "0.00",
    "courier_service_rate": "0.00"
  },
  {
    "id": "f1f416b1-86c5-48e5-8b47-fc87d42fb600",
    "user_id": "d4b5a038-dab9-4b00-8fdf-cbcde292cc94",
    "name": "Kira",
    "type": "expense",
    "color": "#dc2626",
    "icon": "Home",
    "is_default": true,
    "is_active": true,
    "created_at": "2026-01-26T08:58:59.650Z",
    "updated_at": "2026-01-26T08:58:59.650Z",
    "deleted_at": null,
    "expense_type": null,
    "default_channel_id": null,
    "service_commission_rate": "0.00",
    "courier_service_rate": "0.00"
  },
  {
    "id": "494db042-77b0-47d1-9b13-b62a01e6f1f6",
    "user_id": "d4b5a038-dab9-4b00-8fdf-cbcde292cc94",
    "name": "Fatura (Elektrik/Su)",
    "type": "expense",
    "color": "#dc2626",
    "icon": "Zap",
    "is_default": true,
    "is_active": true,
    "created_at": "2026-01-26T08:58:59.650Z",
    "updated_at": "2026-01-26T08:58:59.650Z",
    "deleted_at": null,
    "expense_type": null,
    "default_channel_id": null,
    "service_commission_rate": "0.00",
    "courier_service_rate": "0.00"
  },
  {
    "id": "6601a655-a770-464e-bdb4-19f32a281a65",
    "user_id": "d4b5a038-dab9-4b00-8fdf-cbcde292cc94",
    "name": "Personel Maaşı",
    "type": "expense",
    "color": "#dc2626",
    "icon": "Users",
    "is_default": true,
    "is_active": true,
    "created_at": "2026-01-26T08:58:59.651Z",
    "updated_at": "2026-01-26T08:58:59.651Z",
    "deleted_at": null,
    "expense_type": null,
    "default_channel_id": null,
    "service_commission_rate": "0.00",
    "courier_service_rate": "0.00"
  },
  {
    "id": "1fb7e9c1-dba9-4d99-8df2-c0ad971a5d21",
    "user_id": "d4b5a038-dab9-4b00-8fdf-cbcde292cc94",
    "name": "Malzeme Alımı",
    "type": "expense",
    "color": "#dc2626",
    "icon": "Package",
    "is_default": true,
    "is_active": true,
    "created_at": "2026-01-26T08:58:59.651Z",
    "updated_at": "2026-01-26T08:58:59.651Z",
    "deleted_at": null,
    "expense_type": null,
    "default_channel_id": null,
    "service_commission_rate": "0.00",
    "courier_service_rate": "0.00"
  },
  {
    "id": "f04f9035-d5c6-4c74-9eab-bf28ebef60af",
    "user_id": "d4b5a038-dab9-4b00-8fdf-cbcde292cc94",
    "name": "Diğer Giderler",
    "type": "expense",
    "color": "#dc2626",
    "icon": "MoreHorizontal",
    "is_default": true,
    "is_active": true,
    "created_at": "2026-01-26T08:58:59.652Z",
    "updated_at": "2026-01-26T08:58:59.652Z",
    "deleted_at": null,
    "expense_type": null,
    "default_channel_id": null,
    "service_commission_rate": "0.00",
    "courier_service_rate": "0.00"
  },
  {
    "id": "092a7a41-8e92-4fe3-ba36-f48b656991d8",
    "user_id": "51c6dea5-f8c6-4ea0-9cef-5f568d2c91df",
    "name": "Genel Satış",
    "type": "income",
    "color": "#16a34a",
    "icon": "ShoppingCart",
    "is_default": true,
    "is_active": true,
    "created_at": "2026-01-26T20:58:18.221Z",
    "updated_at": "2026-01-26T20:58:18.221Z",
    "deleted_at": null,
    "expense_type": null,
    "default_channel_id": null,
    "service_commission_rate": "0.00",
    "courier_service_rate": "0.00"
  },
  {
    "id": "062560e7-385f-48b6-8767-07c58fa27c64",
    "user_id": "51c6dea5-f8c6-4ea0-9cef-5f568d2c91df",
    "name": "Personel Maaşı",
    "type": "expense",
    "color": "#dc2626",
    "icon": "Users",
    "is_default": true,
    "is_active": true,
    "created_at": "2026-01-26T20:58:18.229Z",
    "updated_at": "2026-01-26T20:58:18.229Z",
    "deleted_at": null,
    "expense_type": null,
    "default_channel_id": null,
    "service_commission_rate": "0.00",
    "courier_service_rate": "0.00"
  },
  {
    "id": "dc602382-8839-4dfc-8fab-3a6b3b29a8b2",
    "user_id": "51c6dea5-f8c6-4ea0-9cef-5f568d2c91df",
    "name": "Malzeme Alımı",
    "type": "expense",
    "color": "#dc2626",
    "icon": "Package",
    "is_default": true,
    "is_active": true,
    "created_at": "2026-01-26T20:58:18.231Z",
    "updated_at": "2026-01-26T20:58:18.231Z",
    "deleted_at": null,
    "expense_type": null,
    "default_channel_id": null,
    "service_commission_rate": "0.00",
    "courier_service_rate": "0.00"
  },
  {
    "id": "083a2799-305f-4904-8e04-6deaa7f39a09",
    "user_id": "51c6dea5-f8c6-4ea0-9cef-5f568d2c91df",
    "name": "Diğer Giderler",
    "type": "expense",
    "color": "#dc2626",
    "icon": "MoreHorizontal",
    "is_default": true,
    "is_active": true,
    "created_at": "2026-01-26T20:58:18.232Z",
    "updated_at": "2026-01-26T20:58:18.232Z",
    "deleted_at": null,
    "expense_type": null,
    "default_channel_id": null,
    "service_commission_rate": "0.00",
    "courier_service_rate": "0.00"
  },
  {
    "id": "4e6a8125-2527-40b5-a446-55ec37e98644",
    "user_id": "51c6dea5-f8c6-4ea0-9cef-5f568d2c91df",
    "name": "Test verisi",
    "type": "expense",
    "color": "#ef4444",
    "icon": null,
    "is_default": false,
    "is_active": true,
    "created_at": "2026-01-26T20:58:48.517Z",
    "updated_at": "2026-01-26T20:58:48.517Z",
    "deleted_at": "2026-01-26T20:58:54.540Z",
    "expense_type": null,
    "default_channel_id": null,
    "service_commission_rate": "0.00",
    "courier_service_rate": "0.00"
  },
  {
    "id": "6a1ff3c9-0aa7-499e-90fe-3529ddb3e14b",
    "user_id": "51c6dea5-f8c6-4ea0-9cef-5f568d2c91df",
    "name": "Getir",
    "type": "income",
    "color": "#8b5cf6",
    "icon": null,
    "is_default": false,
    "is_active": true,
    "created_at": "2026-01-26T21:26:28.817Z",
    "updated_at": "2026-01-26T21:26:28.817Z",
    "deleted_at": null,
    "expense_type": null,
    "default_channel_id": null,
    "service_commission_rate": "0.00",
    "courier_service_rate": "0.00"
  },
  {
    "id": "58c6fd12-7ee0-4c9f-b42e-c9e4eaec034c",
    "user_id": "51c6dea5-f8c6-4ea0-9cef-5f568d2c91df",
    "name": "Hizmet Geliri",
    "type": "income",
    "color": "#16a34a",
    "icon": "Briefcase",
    "is_default": true,
    "is_active": true,
    "created_at": "2026-01-26T20:58:18.224Z",
    "updated_at": "2026-01-26T20:58:18.224Z",
    "deleted_at": "2026-01-26T21:26:33.230Z",
    "expense_type": null,
    "default_channel_id": null,
    "service_commission_rate": "0.00",
    "courier_service_rate": "0.00"
  },
  {
    "id": "0b561fea-7b4a-478d-bc8f-4d70a168aff2",
    "user_id": "51c6dea5-f8c6-4ea0-9cef-5f568d2c91df",
    "name": "TrendYol",
    "type": "income",
    "color": "#f97316",
    "icon": null,
    "is_default": false,
    "is_active": true,
    "created_at": "2026-01-26T21:26:41.883Z",
    "updated_at": "2026-01-26T21:26:41.883Z",
    "deleted_at": null,
    "expense_type": null,
    "default_channel_id": null,
    "service_commission_rate": "0.00",
    "courier_service_rate": "0.00"
  },
  {
    "id": "7a2e1909-6db7-46ec-85dd-442a9d51ded1",
    "user_id": "51c6dea5-f8c6-4ea0-9cef-5f568d2c91df",
    "name": "Yemek Sepeti",
    "type": "income",
    "color": "#ef4444",
    "icon": null,
    "is_default": false,
    "is_active": true,
    "created_at": "2026-01-26T21:26:51.699Z",
    "updated_at": "2026-01-26T21:26:51.699Z",
    "deleted_at": null,
    "expense_type": null,
    "default_channel_id": null,
    "service_commission_rate": "0.00",
    "courier_service_rate": "0.00"
  },
  {
    "id": "df2374e7-5f54-4f82-82d2-46cbad9ded16",
    "user_id": "51c6dea5-f8c6-4ea0-9cef-5f568d2c91df",
    "name": "Fatura (Elektrik/Su)",
    "type": "expense",
    "color": "#06b6d4",
    "icon": "Zap",
    "is_default": true,
    "is_active": true,
    "created_at": "2026-01-26T20:58:18.228Z",
    "updated_at": "2026-01-27T04:24:18.497Z",
    "deleted_at": null,
    "expense_type": null,
    "default_channel_id": null,
    "service_commission_rate": "0.00",
    "courier_service_rate": "0.00"
  },
  {
    "id": "96b5def7-1dbd-498d-98ae-31d0e08d5931",
    "user_id": "51c6dea5-f8c6-4ea0-9cef-5f568d2c91df",
    "name": "Kira",
    "type": "expense",
    "color": "#8b5cf6",
    "icon": "Home",
    "is_default": true,
    "is_active": true,
    "created_at": "2026-01-26T20:58:18.226Z",
    "updated_at": "2026-01-27T13:14:09.012Z",
    "deleted_at": null,
    "expense_type": null,
    "default_channel_id": null,
    "service_commission_rate": "0.00",
    "courier_service_rate": "0.00"
  },
  {
    "id": "f5f96f5f-b39d-4e1a-a51f-ef6a4d400fb4",
    "user_id": "e0bce7e4-a9a2-4c0e-9841-e11cea1cff57",
    "name": "Kira",
    "type": "expense",
    "color": "#dc2626",
    "icon": "Home",
    "is_default": true,
    "is_active": true,
    "created_at": "2026-01-28T18:19:45.361Z",
    "updated_at": "2026-01-28T18:19:45.361Z",
    "deleted_at": null,
    "expense_type": null,
    "default_channel_id": null,
    "service_commission_rate": "0.00",
    "courier_service_rate": "0.00"
  },
  {
    "id": "0a830cc6-d7c8-4d51-981f-0db7cca476b9",
    "user_id": "e0bce7e4-a9a2-4c0e-9841-e11cea1cff57",
    "name": "Fatura (Elektrik/Su)",
    "type": "expense",
    "color": "#dc2626",
    "icon": "Zap",
    "is_default": true,
    "is_active": true,
    "created_at": "2026-01-28T18:19:45.362Z",
    "updated_at": "2026-01-28T18:19:45.362Z",
    "deleted_at": null,
    "expense_type": null,
    "default_channel_id": null,
    "service_commission_rate": "0.00",
    "courier_service_rate": "0.00"
  },
  {
    "id": "539e81e2-1765-43de-a68e-966190363bf3",
    "user_id": "e0bce7e4-a9a2-4c0e-9841-e11cea1cff57",
    "name": "Personel Maaşı",
    "type": "expense",
    "color": "#dc2626",
    "icon": "Users",
    "is_default": true,
    "is_active": true,
    "created_at": "2026-01-28T18:19:45.363Z",
    "updated_at": "2026-01-28T18:19:45.363Z",
    "deleted_at": null,
    "expense_type": null,
    "default_channel_id": null,
    "service_commission_rate": "0.00",
    "courier_service_rate": "0.00"
  },
  {
    "id": "f4c2b9df-02f5-4e9f-b327-d4147ef73208",
    "user_id": "e0bce7e4-a9a2-4c0e-9841-e11cea1cff57",
    "name": "Malzeme Alımı",
    "type": "expense",
    "color": "#dc2626",
    "icon": "Package",
    "is_default": true,
    "is_active": true,
    "created_at": "2026-01-28T18:19:45.364Z",
    "updated_at": "2026-01-28T18:19:45.364Z",
    "deleted_at": null,
    "expense_type": null,
    "default_channel_id": null,
    "service_commission_rate": "0.00",
    "courier_service_rate": "0.00"
  },
  {
    "id": "040e84b9-af5d-4493-a32d-7159504c729d",
    "user_id": "e0bce7e4-a9a2-4c0e-9841-e11cea1cff57",
    "name": "Diğer Giderler",
    "type": "expense",
    "color": "#dc2626",
    "icon": "MoreHorizontal",
    "is_default": true,
    "is_active": true,
    "created_at": "2026-01-28T18:19:45.365Z",
    "updated_at": "2026-01-28T18:19:45.365Z",
    "deleted_at": null,
    "expense_type": null,
    "default_channel_id": null,
    "service_commission_rate": "0.00",
    "courier_service_rate": "0.00"
  },
  {
    "id": "d93fb8c6-7823-4078-8fba-d4cd2ae94292",
    "user_id": "e0bce7e4-a9a2-4c0e-9841-e11cea1cff57",
    "name": "Yemek Sepeti",
    "type": "income",
    "color": "#ef4444",
    "icon": null,
    "is_default": false,
    "is_active": true,
    "created_at": "2026-01-28T18:44:46.772Z",
    "updated_at": "2026-01-28T18:44:52.006Z",
    "deleted_at": null,
    "expense_type": null,
    "default_channel_id": null,
    "service_commission_rate": "0.00",
    "courier_service_rate": "0.00"
  },
  {
    "id": "0cc87ecc-ec35-4a07-b656-57f2a5defec5",
    "user_id": "e0bce7e4-a9a2-4c0e-9841-e11cea1cff57",
    "name": "Trendyol",
    "type": "income",
    "color": "#f97316",
    "icon": null,
    "is_default": false,
    "is_active": true,
    "created_at": "2026-01-28T18:45:01.479Z",
    "updated_at": "2026-01-28T18:45:01.479Z",
    "deleted_at": null,
    "expense_type": null,
    "default_channel_id": null,
    "service_commission_rate": "0.00",
    "courier_service_rate": "0.00"
  },
  {
    "id": "a8e5883a-7a25-4016-94a6-cc181f5a9a92",
    "user_id": "be8b8541-f427-4287-a00b-a0e9783e5209",
    "name": "dükkan",
    "type": "income",
    "color": "#64748b",
    "icon": null,
    "is_default": false,
    "is_active": true,
    "created_at": "2026-01-29T21:42:43.979Z",
    "updated_at": "2026-01-29T21:42:43.979Z",
    "deleted_at": "2026-01-29T21:54:33.076Z",
    "expense_type": null,
    "default_channel_id": null,
    "service_commission_rate": "0.00",
    "courier_service_rate": "0.00"
  },
  {
    "id": "dc37da5e-02ba-4650-a71c-7fe896541a80",
    "user_id": "be8b8541-f427-4287-a00b-a0e9783e5209",
    "name": "Dükkan Satış",
    "type": "income",
    "color": "#84cc16",
    "icon": null,
    "is_default": false,
    "is_active": true,
    "created_at": "2026-01-24T11:53:18.300Z",
    "updated_at": "2026-01-29T21:54:43.109Z",
    "deleted_at": null,
    "expense_type": null,
    "default_channel_id": null,
    "service_commission_rate": "0.00",
    "courier_service_rate": "0.00"
  },
  {
    "id": "9986f25d-95e0-4fe5-b20c-0553067c4163",
    "user_id": "be8b8541-f427-4287-a00b-a0e9783e5209",
    "name": "Test kategori",
    "type": "expense",
    "color": "#84cc16",
    "icon": null,
    "is_default": false,
    "is_active": true,
    "created_at": "2026-01-26T18:30:00.857Z",
    "updated_at": "2026-01-26T18:30:00.857Z",
    "deleted_at": "2026-01-29T21:55:39.999Z",
    "expense_type": null,
    "default_channel_id": null,
    "service_commission_rate": "0.00",
    "courier_service_rate": "0.00"
  },
  {
    "id": "66c14a88-4f8e-4c3c-94af-c4bafd7d2987",
    "user_id": "be8b8541-f427-4287-a00b-a0e9783e5209",
    "name": "Dİkkan",
    "type": "income",
    "color": "#64748b",
    "icon": null,
    "is_default": false,
    "is_active": true,
    "created_at": "2026-01-29T21:43:01.225Z",
    "updated_at": "2026-01-29T21:43:01.225Z",
    "deleted_at": "2026-01-29T21:55:46.239Z",
    "expense_type": null,
    "default_channel_id": null,
    "service_commission_rate": "0.00",
    "courier_service_rate": "0.00"
  },
  {
    "id": "bb29aa96-7ba6-4db0-9ab9-6af7edcf1912",
    "user_id": "be8b8541-f427-4287-a00b-a0e9783e5209",
    "name": "deneme",
    "type": "income",
    "color": "#64748b",
    "icon": null,
    "is_default": false,
    "is_active": true,
    "created_at": "2026-02-09T06:51:05.238Z",
    "updated_at": "2026-02-09T06:51:05.238Z",
    "deleted_at": "2026-02-09T06:51:18.762Z",
    "expense_type": null,
    "default_channel_id": "305e0b20-dd98-4bde-942f-a1bc0a22e752",
    "service_commission_rate": "0.00",
    "courier_service_rate": "0.00"
  },
  {
    "id": "a9db9d54-87a4-46e1-99dd-6abea3ba9cbb",
    "user_id": "be8b8541-f427-4287-a00b-a0e9783e5209",
    "name": "test",
    "type": "income",
    "color": "#71717a",
    "icon": null,
    "is_default": false,
    "is_active": true,
    "created_at": "2026-02-09T06:51:32.618Z",
    "updated_at": "2026-02-09T06:51:32.618Z",
    "deleted_at": "2026-02-09T06:51:36.576Z",
    "expense_type": null,
    "default_channel_id": "305e0b20-dd98-4bde-942f-a1bc0a22e752",
    "service_commission_rate": "0.00",
    "courier_service_rate": "0.00"
  },
  {
    "id": "e2ddde0e-1de0-4298-ba4b-8260233011a1",
    "user_id": "e0bce7e4-a9a2-4c0e-9841-e11cea1cff57",
    "name": "Hizmet Geliri",
    "type": "income",
    "color": "#16a34a",
    "icon": "Briefcase",
    "is_default": true,
    "is_active": true,
    "created_at": "2026-01-28T18:19:45.360Z",
    "updated_at": "2026-01-28T18:19:45.360Z",
    "deleted_at": "2026-02-09T12:48:01.396Z",
    "expense_type": null,
    "default_channel_id": null,
    "service_commission_rate": "0.00",
    "courier_service_rate": "0.00"
  },
  {
    "id": "0372131f-9eaa-4f02-a7ef-abe14149a2df",
    "user_id": "e0bce7e4-a9a2-4c0e-9841-e11cea1cff57",
    "name": "Genel Satış",
    "type": "income",
    "color": "#16a34a",
    "icon": "ShoppingCart",
    "is_default": true,
    "is_active": true,
    "created_at": "2026-01-28T18:19:45.357Z",
    "updated_at": "2026-01-28T18:19:45.357Z",
    "deleted_at": "2026-02-09T12:48:04.387Z",
    "expense_type": null,
    "default_channel_id": null,
    "service_commission_rate": "0.00",
    "courier_service_rate": "0.00"
  },
  {
    "id": "79c62556-4555-483b-97fe-96eb4129f531",
    "user_id": "e0bce7e4-a9a2-4c0e-9841-e11cea1cff57",
    "name": "Mağaza",
    "type": "income",
    "color": "#ef4444",
    "icon": null,
    "is_default": false,
    "is_active": true,
    "created_at": "2026-02-09T12:49:14.577Z",
    "updated_at": "2026-02-09T12:49:36.516Z",
    "deleted_at": null,
    "expense_type": null,
    "default_channel_id": null,
    "service_commission_rate": "0.00",
    "courier_service_rate": "0.00"
  },
  {
    "id": "0ed57563-9b15-4216-af6d-43070cd95b5e",
    "user_id": "e0bce7e4-a9a2-4c0e-9841-e11cea1cff57",
    "name": "Getir",
    "type": "income",
    "color": "#8b5cf6",
    "icon": null,
    "is_default": false,
    "is_active": true,
    "created_at": "2026-01-28T18:44:36.723Z",
    "updated_at": "2026-02-09T12:54:04.498Z",
    "deleted_at": null,
    "expense_type": null,
    "default_channel_id": "0cf763c5-9bd7-42a7-abb2-e91e64320665",
    "service_commission_rate": "0.00",
    "courier_service_rate": "0.00"
  },
  {
    "id": "2a9af643-f7f1-4956-a329-153471331f8a",
    "user_id": "be8b8541-f427-4287-a00b-a0e9783e5209",
    "name": "test",
    "type": "income",
    "color": "#0ea5e9",
    "icon": null,
    "is_default": false,
    "is_active": true,
    "created_at": "2026-02-09T20:09:11.368Z",
    "updated_at": "2026-02-09T20:09:11.368Z",
    "deleted_at": "2026-02-09T20:09:15.394Z",
    "expense_type": null,
    "default_channel_id": null,
    "service_commission_rate": "0.00",
    "courier_service_rate": "0.00"
  },
  {
    "id": "85a0e973-3b81-46ee-938c-cf1ba996dc1c",
    "user_id": "be8b8541-f427-4287-a00b-a0e9783e5209",
    "name": "Sistem-Getir",
    "type": "expense",
    "color": "#64748b",
    "icon": null,
    "is_default": false,
    "is_active": true,
    "created_at": "2026-02-09T20:47:23.510Z",
    "updated_at": "2026-02-09T20:47:23.510Z",
    "deleted_at": null,
    "expense_type": null,
    "default_channel_id": null,
    "service_commission_rate": "0.00",
    "courier_service_rate": "0.00"
  },
  {
    "id": "3b61eb52-4b64-40df-ad80-f2bfee978b3b",
    "user_id": "be8b8541-f427-4287-a00b-a0e9783e5209",
    "name": "Sistem-Yemek Sepeti",
    "type": "expense",
    "color": "#64748b",
    "icon": null,
    "is_default": false,
    "is_active": true,
    "created_at": "2026-02-10T18:31:08.096Z",
    "updated_at": "2026-02-10T18:31:08.096Z",
    "deleted_at": null,
    "expense_type": null,
    "default_channel_id": null,
    "service_commission_rate": "0.00",
    "courier_service_rate": "0.00"
  },
  {
    "id": "74ebce92-7e81-43ba-8c11-406b76c345a5",
    "user_id": "be8b8541-f427-4287-a00b-a0e9783e5209",
    "name": "Sistem-Kredi kartı",
    "type": "expense",
    "color": "#f59e0b",
    "icon": null,
    "is_default": false,
    "is_active": true,
    "created_at": "2026-02-10T19:16:25.302Z",
    "updated_at": "2026-02-10T19:16:25.302Z",
    "deleted_at": null,
    "expense_type": null,
    "default_channel_id": null,
    "service_commission_rate": "0.00",
    "courier_service_rate": "0.00"
  }
]